collate_sqllineage/__init__.py
collate_sqllineage/cli.py
collate_sqllineage/drawing.py
collate_sqllineage/exceptions.py
collate_sqllineage/io.py
collate_sqllineage/runner.py
collate_sqllineage/core/__init__.py
collate_sqllineage/core/analyzer.py
collate_sqllineage/core/holders.py
collate_sqllineage/core/models.py
collate_sqllineage/core/parser/__init__.py
collate_sqllineage/core/parser/sqlfluff/__init__.py
collate_sqllineage/core/parser/sqlfluff/analyzer.py
collate_sqllineage/core/parser/sqlfluff/holder_utils.py
collate_sqllineage/core/parser/sqlfluff/models.py
collate_sqllineage/core/parser/sqlfluff/utils.py
collate_sqllineage/core/parser/sqlfluff/extractors/__init__.py
collate_sqllineage/core/parser/sqlfluff/extractors/cte_extractor.py
collate_sqllineage/core/parser/sqlfluff/extractors/ddl_alter_extractor.py
collate_sqllineage/core/parser/sqlfluff/extractors/ddl_drop_extractor.py
collate_sqllineage/core/parser/sqlfluff/extractors/dml_insert_extractor.py
collate_sqllineage/core/parser/sqlfluff/extractors/dml_merge_extractor.py
collate_sqllineage/core/parser/sqlfluff/extractors/dml_select_extractor.py
collate_sqllineage/core/parser/sqlfluff/extractors/lineage_holder_extractor.py
collate_sqllineage/core/parser/sqlfluff/extractors/noop_extractor.py
collate_sqllineage/core/parser/sqlfluff/handlers/__init__.py
collate_sqllineage/core/parser/sqlfluff/handlers/base.py
collate_sqllineage/core/parser/sqlfluff/handlers/source.py
collate_sqllineage/core/parser/sqlfluff/handlers/swap_partition.py
collate_sqllineage/core/parser/sqlfluff/handlers/target.py
collate_sqllineage/core/parser/sqlglot/__init__.py
collate_sqllineage/core/parser/sqlglot/analyzer.py
collate_sqllineage/core/parser/sqlglot/holder_utils.py
collate_sqllineage/core/parser/sqlglot/models.py
collate_sqllineage/core/parser/sqlglot/utils.py
collate_sqllineage/core/parser/sqlglot/extractors/__init__.py
collate_sqllineage/core/parser/sqlglot/extractors/copy_extractor.py
collate_sqllineage-2.0.1.dist-info/METADATA
collate_sqllineage-2.0.1.dist-info/WHEEL
collate_sqllineage-2.0.1.dist-info/entry_points.txt
collate_sqllineage-2.0.1.dist-info/top_level.txt
collate_sqllineage-2.0.1.dist-info/RECORD
