Metadata-Version: 2.4
Name: collate-sqllineage
Version: 2.0.1
Summary: Collate SQL Lineage for Analysis Tool powered by Python and sqlfluff based on sqllineage.
Author: Collate Committers
Classifier: Development Status :: 5 - Production/Stable
Classifier: License :: OSI Approved :: MIT License
Classifier: Operating System :: OS Independent
Classifier: Programming Language :: Python :: 3
Classifier: Programming Language :: Python :: 3.9
Classifier: Programming Language :: Python :: 3.10
Classifier: Programming Language :: Python :: 3.11
Classifier: Programming Language :: Python :: Implementation :: CPython
Requires-Python: >=3.9
Requires-Dist: sqlparse==0.5.3
Requires-Dist: networkx>=2.4
Requires-Dist: collate-sqlfluff~=3.3.0
Requires-Dist: sqlglot<28.0.0,>=27.29.0
Provides-Extra: ci
Requires-Dist: bandit; extra == "ci"
Requires-Dist: black; extra == "ci"
Requires-Dist: flake8; extra == "ci"
Requires-Dist: flake8-blind-except; extra == "ci"
Requires-Dist: flake8-builtins; extra == "ci"
Requires-Dist: flake8-import-order; extra == "ci"
Requires-Dist: flake8-logging-format; extra == "ci"
Requires-Dist: mypy; extra == "ci"
Requires-Dist: pytest; extra == "ci"
Requires-Dist: pytest-cov; extra == "ci"
Requires-Dist: tox; extra == "ci"
Requires-Dist: twine; extra == "ci"
Requires-Dist: wheel; extra == "ci"
Provides-Extra: docs
Requires-Dist: Sphinx>=3.2.0; extra == "docs"
Requires-Dist: sphinx_rtd_theme>=0.5.0; extra == "docs"
Dynamic: author
Dynamic: classifier
Dynamic: description
Dynamic: description-content-type
Dynamic: provides-extra
Dynamic: requires-dist
Dynamic: requires-python
Dynamic: summary
